
{
    
    "Microsoft.Synapse/workspaces/notebooks": {
        "properties": {
            "bigDataPool": {
                "referenceName": "="
            }
        }
    },
    "Microsoft.Synapse/workspaces/sqlscripts": {
        "properties": {
            "content": {
                "currentConnection": {
                    "*": "-"
                }
            }
        }
    },
    "Microsoft.Synapse/workspaces/pipelines": {
        "properties": {
            "activities": [{
                "typeProperties": {
                    "waitTimeInSeconds": "-::int",
                    "headers": "=::object",
                    "activities": [
                        {
                            "typeProperties": {
                                "url": "-:-webUrl:string"
                            }
                        }
                    ]
                    
                    "parameters": [
                        {
                            "typeProperties": {
                                "*": "="
                            }
                        }
                    ]
                    
                    
                    
                }
            }]
        }
    },
    "Microsoft.Synapse/workspaces/integrationRuntimes": {
        "properties": {
            "typeProperties": {
                "*": "="
            }
        }
    },
    "Microsoft.Synapse/workspaces/triggers": {
        "properties": {
            "typeProperties": {
                "recurrence": {
                    "*": "=",
                    "interval": "=:triggerSuffix:int",
                    "frequency": "=:-freq"
                },
                "maxConcurrency": "="
            }
        }
    },
    
    
    "Microsoft.Synapse/workspaces/linkedServices": {
        "*": {
            "properties": {
                "typeProperties": {
                    "accountName": "=",
                    "username": "=",
                    "userName": "=",
                    "accessKeyId": "=",
                    "endpoint": "=",
                    "servicePrincipalId": "=",
                    "userId": "=",
                    "host": "=",
                    "clientId": "=",
                    "clusterUserName": "=",
                    "clusterSshUserName": "=",
                    "hostSubscriptionId": "=",
                    "clusterResourceGroup": "=",
                    "subscriptionId": "=",
                    "resourceGroupName": "=",
                    "tenant": "=",
                    "dataLakeStoreUri": "=",
                    "baseUrl": "=",
                    "database": "=",
                    "serviceEndpoint": "=",
                    "batchUri": "=",
                    "poolName": "=",
                    "databaseName": "=",
                    "systemNumber": "=",
                    "server": "=",
                    "url": "=",
                    "functionAppUrl": "=",
                    "environmentUrl": "=",
                    "aadResourceId": "=",
                    "sasUri": "|:-sasUri:secureString",
                    "sasToken": "|",
                    "connectionString": "|:-connectionString:secureString",
                    "hostKeyFingerprint": "=",
                    "domain": "=",
                    "workspaceResourceId": "="                    
                }
            }
        },
        "AzureDataLakeStore": {
            "properties": {
                "typeProperties": {
                    "dataLakeStoreUri": "="
                }
            }
        },
        "AzureKeyVault": {
            "properties": {
                "typeProperties": {
                    "baseUrl": "|:baseUrl:secureString"
                },
                "parameters": {
                    "KeyVaultURL": {
                        "type": "=",
                        "defaultValue": "|:defaultValue:secureString"
                    }
                }
            }
        }
    },
    "Microsoft.Synapse/workspaces/datasets": {
        "properties": {
            "typeProperties": {
                "*": "="
            }
        }
    },
    "Microsoft.Synapse/workspaces/credentials" : {
        "properties": {
            "typeProperties": {
                "resourceId": "="
            }
        }
    }
}
